logger/__init__.py
logger/fancy_logger.py
brand_new_fancy_logger-0.0.4.dist-info/METADATA
brand_new_fancy_logger-0.0.4.dist-info/WHEEL
brand_new_fancy_logger-0.0.4.dist-info/top_level.txt
brand_new_fancy_logger-0.0.4.dist-info/RECORD
